[{"kind": "customsearch#result", "title": "Brazil truckers jam traffic to protest Bolsonaro loss | World News ...", "htmlTitle": "Brazil truckers jam traffic to protest Bolsonaro loss | World News ...", "link": "https://images.indianexpress.com/2022/11/Brazil_Elections_1200.jpg?w=414", "displayLink": "indianexpress.com", "snippet": "Brazil truckers jam traffic to protest Bolsonaro loss | World News ...", "htmlSnippet": "Brazil truckers jam traffic to protest Bolsonaro loss | World News ...", "mime": "image/jpeg", "fileFormat": "image/jpeg", "image": {"contextLink": "https://indianexpress.com/article/world/brazil-truckers-jam-traffic-protest-bolsonaro-loss-8243382/", "height": 230, "width": 414, "byteSize": 18881, "thumbnailLink": "https://encrypted-tbn0.gstatic.com/images?q=tbn:ANd9GcRUp2cE6Td5JeKcwH7y8Rvb2s9LAp72WknfwOx3KmxD9MXp6mQ9seFn&s", "thumbnailHeight": 69, "thumbnailWidth": 125}}, {"kind": "customsearch#result", "title": "Brazil truckers jam traffic to protest Bolsonaro loss - The Bridge", "htmlTitle": "Brazil truckers jam traffic to protest Bolsonaro loss - The Bridge", "link": "https://secure.gravatar.com/avatar/ec5113578355b19a239e0b9887fd3d03?s=96&d=mm&r=g", "displayLink": "13angle.com", "snippet": "Brazil truckers jam traffic to protest Bolsonaro loss - The Bridge", "htmlSnippet": "Brazil truckers jam traffic to protest Bolsonaro loss - The Bridge", "mime": "image/", "fileFormat": "image/", "image": {"contextLink": "https://13angle.com/blog/news/international-news/brazil-truckers-jam-traffic-to-protest-bolsonaro-loss/", "height": 96, "width": 96, "byteSize": 1528, "thumbnailLink": "https://encrypted-tbn0.gstatic.com/images?q=tbn:ANd9GcRDjLbBKRkMSE0jazgrOcYUVueL8gJ1gcHGhYv1JBCbTtnM8MdPYEDS&s", "thumbnailHeight": 81, "thumbnailWidth": 81}}, {"kind": "customsearch#result", "title": "Brazil truckers jam traffic to protest Bolsonaro loss | World News ...", "htmlTitle": "Brazil truckers jam traffic to protest Bolsonaro loss | World News ...", "link": "https://images.indianexpress.com/2022/11/Brazil_Elections_1200.jpg", "displayLink": "indianexpress.com", "snippet": "Brazil truckers jam traffic to protest Bolsonaro loss | World News ...", "htmlSnippet": "Brazil truckers jam traffic to protest Bolsonaro loss | World News ...", "mime": "image/jpeg", "fileFormat": "image/jpeg", "image": {"contextLink": "https://indianexpress.com/article/world/brazil-truckers-jam-traffic-protest-bolsonaro-loss-8243382/", "height": 667, "width": 1200, "byteSize": 112558, "thumbnailLink": "https://encrypted-tbn0.gstatic.com/images?q=tbn:ANd9GcQxeI-m-q9zCKkOOkqcXnR6Xoqn8SjgzILZXt3xKqGGJyj-eKPq0EQQZQ&s", "thumbnailHeight": 83, "thumbnailWidth": 150}}, {"kind": "customsearch#result", "title": "Brazil truckers jam traffic to protest Bolsonaro loss | World News ...", "htmlTitle": "Brazil truckers jam traffic to protest Bolsonaro loss | World News ...", "link": "https://images.indianexpress.com/2022/11/Brazil_Elections_1200.jpg?w=389", "displayLink": "indianexpress.com", "snippet": "Brazil truckers jam traffic to protest Bolsonaro loss | World News ...", "htmlSnippet": "Brazil truckers jam traffic to protest Bolsonaro loss | World News ...", "mime": "image/jpeg", "fileFormat": "image/jpeg", "image": {"contextLink": "https://indianexpress.com/article/world/brazil-truckers-jam-traffic-protest-bolsonaro-loss-8243382/", "height": 216, "width": 389, "byteSize": 17052, "thumbnailLink": "https://encrypted-tbn0.gstatic.com/images?q=tbn:ANd9GcRCpmwjwoOFvFHdzD3tRI_GT8N8NINw420XovnehY87HksbOFRoOTeY-A&s", "thumbnailHeight": 68, "thumbnailWidth": 123}}, {"kind": "customsearch#result", "title": "World News: Latest International News, World News Today Headlines ...", "htmlTitle": "World News: Latest International News, World News Today Headlines ...", "link": "https://images.indianexpress.com/2022/11/Brazil_Elections_1200.jpg?w=316", "displayLink": "indianexpress.com", "snippet": "World News: Latest International News, World News Today Headlines ...", "htmlSnippet": "World News: Latest International News, World News Today Headlines ...", "mime": "image/jpeg", "fileFormat": "image/jpeg", "image": {"contextLink": "https://indianexpress.com/section/World/page/114/", "height": 175, "width": 316, "byteSize": 12086, "thumbnailLink": "https://encrypted-tbn0.gstatic.com/images?q=tbn:ANd9GcSSfQl9opUxQx9aI_GjKJRVuSk6-aqjug9ohFRqLTs8tyF2_y9LOA4e&s", "thumbnailHeight": 65, "thumbnailWidth": 117}}, {"kind": "customsearch#result", "title": "World News: Latest International News, World News Today Headlines ...", "htmlTitle": "World News: Latest International News, World News Today Headlines ...", "link": "https://images.indianexpress.com/2022/11/liz-truss.jpg?w=316", "displayLink": "indianexpress.com", "snippet": "World News: Latest International News, World News Today Headlines ...", "htmlSnippet": "World News: Latest International News, World News Today Headlines ...", "mime": "image/jpeg", "fileFormat": "image/jpeg", "image": {"contextLink": "https://indianexpress.com/section/World/page/114/", "height": 175, "width": 316, "byteSize": 10342, "thumbnailLink": "https://encrypted-tbn0.gstatic.com/images?q=tbn:ANd9GcS8jAu6qIknV1avfNWskPY_swzZ_iMTnEFpo104UD66dzt5ZE4wQiuzHw&s", "thumbnailHeight": 65, "thumbnailWidth": 117}}, {"kind": "customsearch#result", "title": "World News: Latest International News, World News Today Headlines ...", "htmlTitle": "World News: Latest International News, World News Today Headlines ...", "link": "https://images.indianexpress.com/2022/11/Koreas_Tensions_61447-311b2.jpg?w=316", "displayLink": "indianexpress.com", "snippet": "World News: Latest International News, World News Today Headlines ...", "htmlSnippet": "World News: Latest International News, World News Today Headlines ...", "mime": "image/jpeg", "fileFormat": "image/jpeg", "image": {"contextLink": "https://indianexpress.com/section/world/page/132/?utm_source", "height": 175, "width": 316, "byteSize": 12178, "thumbnailLink": "https://encrypted-tbn0.gstatic.com/images?q=tbn:ANd9GcQppsymUIU2vuJWApdKDuIKbyXMrn-yxdem3SzwHFckdL_cOO8fDHkYyg&s", "thumbnailHeight": 65, "thumbnailWidth": 117}}, {"kind": "customsearch#result", "title": "World News: Latest International News, World News Today Headlines ...", "htmlTitle": "World News: Latest International News, World News Today Headlines ...", "link": "https://images.indianexpress.com/2022/11/Korea_missile_1200.jpg?w=316", "displayLink": "indianexpress.com", "snippet": "World News: Latest International News, World News Today Headlines ...", "htmlSnippet": "World News: Latest International News, World News Today Headlines ...", "mime": "image/jpeg", "fileFormat": "image/jpeg", "image": {"contextLink": "https://indianexpress.com/section/world/page/133/?device=desktop", "height": 176, "width": 316, "byteSize": 3112, "thumbnailLink": "https://encrypted-tbn0.gstatic.com/images?q=tbn:ANd9GcQ_n9G9B6I1dfZ-tOjAIdEM9OjIomj1uppNhpn4KPuR_1qqX82z-lMLGg&s", "thumbnailHeight": 65, "thumbnailWidth": 117}}, {"kind": "customsearch#result", "title": "World News: Latest International News, World News Today Headlines ...", "htmlTitle": "World News: Latest International News, World News Today Headlines ...", "link": "https://images.indianexpress.com/2022/11/rohan-murthy.jpg?w=316", "displayLink": "indianexpress.com", "snippet": "World News: Latest International News, World News Today Headlines ...", "htmlSnippet": "World News: Latest International News, World News Today Headlines ...", "mime": "image/jpeg", "fileFormat": "image/jpeg", "image": {"contextLink": "https://indianexpress.com/section/world/page/132/?utm_source", "height": 175, "width": 316, "byteSize": 12009, "thumbnailLink": "https://encrypted-tbn0.gstatic.com/images?q=tbn:ANd9GcRgHPFyMBhaY8U6VZ2b6XBIbnUe84YpnOWPlXq96LaRqCEtz5OvSrx6dA&s", "thumbnailHeight": 65, "thumbnailWidth": 117}}, {"kind": "customsearch#result", "title": "World News: Latest International News, World News Today Headlines ...", "htmlTitle": "World News: Latest International News, World News Today Headlines ...", "link": "https://images.indianexpress.com/2022/11/missile-korea.jpg?w=316", "displayLink": "indianexpress.com", "snippet": "World News: Latest International News, World News Today Headlines ...", "htmlSnippet": "World News: Latest International News, World News Today Headlines ...", "mime": "image/jpeg", "fileFormat": "image/jpeg", "image": {"contextLink": "https://indianexpress.com/section/world/page/133/?device=desktop", "height": 175, "width": 316, "byteSize": 7039, "thumbnailLink": "https://encrypted-tbn0.gstatic.com/images?q=tbn:ANd9GcRB5Ry39lly3buyFJYjPWrEb8MwgyCtBz5C52uHbBgZBpcC3pRbZcsv&s", "thumbnailHeight": 65, "thumbnailWidth": 117}}]