[{"kind": "customsearch#result", "title": "Creepy Barbies Sale, SAVE 42% - horiconphoenix.com", "htmlTitle": "Creepy Barbies Sale, SAVE 42% - horiconphoenix.<b>com</b>", "link": "https://metro.co.uk/wp-content/uploads/2015/03/ad_162746502.jpg", "displayLink": "horiconphoenix.com", "snippet": "Creepy Barbies Sale, SAVE 42% - horiconphoenix.com", "htmlSnippet": "Creepy Barbies Sale, SAVE 42% - horiconphoenix.<b>com</b>", "mime": "image/jpeg", "fileFormat": "image/jpeg", "image": {"contextLink": "https://horiconphoenix.com/?items=creepy+barbies_MTRfMTBfMjI1NjQzOF80NQ==", "height": 712, "width": 534, "byteSize": 50303, "thumbnailLink": "https://encrypted-tbn0.gstatic.com/images?q=tbn:ANd9GcSFnGLI_peFOyCIEMeo3qptWpoUPKtT5JbakpQ5PeG7U9AmupE7xcL2mg&s", "thumbnailHeight": 140, "thumbnailWidth": 105}}, {"kind": "customsearch#result", "title": "Creepy Barbies Sale, SAVE 42% - horiconphoenix.com", "htmlTitle": "Creepy Barbies Sale, SAVE 42% - horiconphoenix.<b>com</b>", "link": "https://i.pinimg.com/originals/54/89/7f/54897fafc946138796bb5d258d14f7be.jpg", "displayLink": "horiconphoenix.com", "snippet": "Creepy Barbies Sale, SAVE 42% - horiconphoenix.com", "htmlSnippet": "Creepy Barbies Sale, SAVE 42% - horiconphoenix.<b>com</b>", "mime": "image/jpeg", "fileFormat": "image/jpeg", "image": {"contextLink": "https://horiconphoenix.com/?items=creepy+barbies_MTRfMTBfMjI1NjQzOF80NQ==", "height": 638, "width": 500, "byteSize": 56653, "thumbnailLink": "https://encrypted-tbn0.gstatic.com/images?q=tbn:ANd9GcTYFXVCKFH82s1VW2e1Eub0rcWmVzKDqCnOdSnwqCoZSjDvKfwDLqkehvI&s", "thumbnailHeight": 137, "thumbnailWidth": 107}}, {"kind": "customsearch#result", "title": "Creepy Barbies Sale, SAVE 42% - horiconphoenix.com", "htmlTitle": "Creepy Barbies Sale, SAVE 42% - horiconphoenix.<b>com</b>", "link": "https://www.yourtango.com/sites/default/files/styles/header_slider/public/image_node_gallery_gallery/830464_313350435434565_911756204_o.jpg", "displayLink": "horiconphoenix.com", "snippet": "Creepy Barbies Sale, SAVE 42% - horiconphoenix.com", "htmlSnippet": "Creepy Barbies Sale, SAVE 42% - horiconphoenix.<b>com</b>", "mime": "image/jpeg", "fileFormat": "image/jpeg", "image": {"contextLink": "https://horiconphoenix.com/?items=creepy+barbies_MTRfMTBfMjI1NjQzOF80NQ==", "height": 386, "width": 774, "byteSize": 29069, "thumbnailLink": "https://encrypted-tbn0.gstatic.com/images?q=tbn:ANd9GcRx97sorsJno9ayrsIC0ElD3p0sT-zfVXpnii-2ioFLQqo4HXoVGcJOpJA&s", "thumbnailHeight": 71, "thumbnailWidth": 142}}, {"kind": "customsearch#result", "title": "Creepy Barbies Sale, SAVE 42% - horiconphoenix.com", "htmlTitle": "Creepy Barbies Sale, SAVE 42% - horiconphoenix.<b>com</b>", "link": "https://i.ytimg.com/vi/vR3tMLVBwMI/maxresdefault.jpg", "displayLink": "horiconphoenix.com", "snippet": "Creepy Barbies Sale, SAVE 42% - horiconphoenix.com", "htmlSnippet": "Creepy Barbies Sale, SAVE 42% - horiconphoenix.<b>com</b>", "mime": "image/jpeg", "fileFormat": "image/jpeg", "image": {"contextLink": "https://horiconphoenix.com/?items=creepy+barbies_MTRfMTBfMjI1NjQzOF80NQ==", "height": 720, "width": 1280, "byteSize": 395053, "thumbnailLink": "https://encrypted-tbn0.gstatic.com/images?q=tbn:ANd9GcSb6qSXKfrlip0joVhrPWR3LFM-yErAYUFZS9dbrjzgTyPQ7jUU_3d4cr8&s", "thumbnailHeight": 84, "thumbnailWidth": 150}}, {"kind": "customsearch#result", "title": "Creepy Barbies Sale, SAVE 42% - horiconphoenix.com", "htmlTitle": "Creepy Barbies Sale, SAVE 42% - horiconphoenix.<b>com</b>", "link": "https://thumbor.forbes.com/thumbor/fit-in/1200x0/filters%3Aformat%28jpg%29/https%3A%2F%2Fspecials-images.forbesimg.com%2Fimageserve%2F492136576%2F0x0.jpg%3Ffit%3Dscale", "displayLink": "horiconphoenix.com", "snippet": "Creepy Barbies Sale, SAVE 42% - horiconphoenix.com", "htmlSnippet": "Creepy Barbies Sale, SAVE 42% - horiconphoenix.<b>com</b>", "mime": "image/", "fileFormat": "image/", "image": {"contextLink": "https://horiconphoenix.com/?items=creepy+barbies_MTRfMTBfMjI1NjQzOF80NQ==", "height": 754, "width": 1200, "byteSize": 125755, "thumbnailLink": "https://encrypted-tbn0.gstatic.com/images?q=tbn:ANd9GcSuj9AyqEkgsWcpKflGTLapoyhOl5q96izMJgUnhPt7bsI8PJ8FZ9PPpg&s", "thumbnailHeight": 94, "thumbnailWidth": 150}}, {"kind": "customsearch#result", "title": "Creepy Barbies Sale, SAVE 42% - horiconphoenix.com", "htmlTitle": "Creepy Barbies Sale, SAVE 42% - horiconphoenix.<b>com</b>", "link": "https://i.pinimg.com/originals/59/6c/e3/596ce3917f0af98dce38a675979dd1ad.jpg", "displayLink": "horiconphoenix.com", "snippet": "Creepy Barbies Sale, SAVE 42% - horiconphoenix.com", "htmlSnippet": "Creepy Barbies Sale, SAVE 42% - horiconphoenix.<b>com</b>", "mime": "image/jpeg", "fileFormat": "image/jpeg", "image": {"contextLink": "https://horiconphoenix.com/?items=creepy+barbies_MTRfMTBfMjI1NjQzOF80NQ==", "height": 550, "width": 445, "byteSize": 39891, "thumbnailLink": "https://encrypted-tbn0.gstatic.com/images?q=tbn:ANd9GcSaZwzE0WjoiXCGuedntjJCckLYtWgSQPYQnlFvecMAXl6cdgpHHljsBfo&s", "thumbnailHeight": 133, "thumbnailWidth": 108}}, {"kind": "customsearch#result", "title": "Creepy Barbies Shop, SAVE 46% - baltijaskrasti.lv", "htmlTitle": "Creepy Barbies Shop, SAVE 46% - baltijaskrasti.lv", "link": "https://www.yourtango.com/sites/default/files/styles/header_slider/public/image_blog/exotic%20barbie_0.jpg", "displayLink": "baltijaskrasti.lv", "snippet": "Creepy Barbies Shop, SAVE 46% - baltijaskrasti.lv", "htmlSnippet": "Creepy Barbies Shop, SAVE 46% - baltijaskrasti.lv", "mime": "image/jpeg", "fileFormat": "image/jpeg", "image": {"contextLink": "https://baltijaskrasti.lv/?items=creepy+barbies_Nl8yOV8yNDU3MDQxXzQ4", "height": 386, "width": 774, "byteSize": 29128, "thumbnailLink": "https://encrypted-tbn0.gstatic.com/images?q=tbn:ANd9GcQtNNGQvtnU0IBaeYArxrmJReh3Q0Jrmc_JxZDQjhQqiOdHFAowl8aF_8w&s", "thumbnailHeight": 71, "thumbnailWidth": 142}}, {"kind": "customsearch#result", "title": "Creepy Barbies Shop, SAVE 46% - baltijaskrasti.lv", "htmlTitle": "Creepy Barbies Shop, SAVE 46% - baltijaskrasti.lv", "link": "https://media2.s-nbcnews.com/j/MSNBC/Components/Video/__NEW/x_tdy_orig_barbie_pepitone_150917.focal-760x428.jpg", "displayLink": "baltijaskrasti.lv", "snippet": "Creepy Barbies Shop, SAVE 46% - baltijaskrasti.lv", "htmlSnippet": "Creepy Barbies Shop, SAVE 46% - baltijaskrasti.lv", "mime": "image/jpeg", "fileFormat": "image/jpeg", "image": {"contextLink": "https://baltijaskrasti.lv/?items=creepy+barbies_Nl8yOV8yNDU3MDQxXzQ4", "height": 428, "width": 760, "byteSize": 69789, "thumbnailLink": "https://encrypted-tbn0.gstatic.com/images?q=tbn:ANd9GcSjHcUigEuw0jvS36oVrvYaSjWKo4MyWBWwztBPMJoY9xDiM34C8ryZDFg&s", "thumbnailHeight": 80, "thumbnailWidth": 142}}, {"kind": "customsearch#result", "title": "Creepy Barbies Shop, SAVE 46% - baltijaskrasti.lv", "htmlTitle": "Creepy Barbies Shop, SAVE 46% - baltijaskrasti.lv", "link": "https://i.ytimg.com/vi/MZUJRDIrSJo/maxresdefault.jpg", "displayLink": "baltijaskrasti.lv", "snippet": "Creepy Barbies Shop, SAVE 46% - baltijaskrasti.lv", "htmlSnippet": "Creepy Barbies Shop, SAVE 46% - baltijaskrasti.lv", "mime": "image/jpeg", "fileFormat": "image/jpeg", "image": {"contextLink": "https://baltijaskrasti.lv/?items=creepy+barbies_Nl8yOV8yNDU3MDQxXzQ4", "height": 720, "width": 1280, "byteSize": 62066, "thumbnailLink": "https://encrypted-tbn0.gstatic.com/images?q=tbn:ANd9GcSPjY8ZMiTDaClsd3_HtK4Bg79_Y7f1bd3Iz2RCFtfYmMccQXKu_HLdwvw&s", "thumbnailHeight": 84, "thumbnailWidth": 150}}, {"kind": "customsearch#result", "title": "Creepy Barbies Shop, SAVE 46% - baltijaskrasti.lv", "htmlTitle": "Creepy Barbies Shop, SAVE 46% - baltijaskrasti.lv", "link": "https://www.etonline.com/sites/default/files/styles/max_970x546/public/images/2014-11/set_barbie_640.jpg", "displayLink": "baltijaskrasti.lv", "snippet": "Creepy Barbies Shop, SAVE 46% - baltijaskrasti.lv", "htmlSnippet": "Creepy Barbies Shop, SAVE 46% - baltijaskrasti.lv", "mime": "image/jpeg", "fileFormat": "image/jpeg", "image": {"contextLink": "https://baltijaskrasti.lv/?items=creepy+barbies_Nl8yOV8yNDU3MDQxXzQ4", "height": 546, "width": 970, "byteSize": 47647, "thumbnailLink": "https://encrypted-tbn0.gstatic.com/images?q=tbn:ANd9GcRlB6-G59JFMhvuBjow6GpcSRC8WdmWOTcnp9wOVK6org-EDFwls1OCmpI&s", "thumbnailHeight": 84, "thumbnailWidth": 149}}]