[{"kind": "customsearch#result", "title": "Obamas Serve Thanksgiving Dinner to the Homeless", "htmlTitle": "Obamas Serve Thanksgiving Dinner to the Homeless", "link": "http://m.wsj.net/video/20151126/112615obathanksgiving2/112615obathanksgiving2_1280x720.jpg", "displayLink": "www.wsj.com", "snippet": "Obamas Serve Thanksgiving Dinner to the Homeless", "htmlSnippet": "Obamas Serve Thanksgiving Dinner to the Homeless", "mime": "image/jpeg", "fileFormat": "image/jpeg", "image": {"contextLink": "https://www.wsj.com/video/obamas-serve-thanksgiving-dinner-to-the-homeless/3406E0AA-155A-4248-8C2C-796CCA4D472C.html", "height": 720, "width": 1280, "byteSize": 121688, "thumbnailLink": "https://encrypted-tbn0.gstatic.com/images?q=tbn:ANd9GcQnPsYPj6rnuZ7UlX3N0fqHfjWbC-6FOxqdv2tevkPqSCfddp5mvMbpAA&s", "thumbnailHeight": 84, "thumbnailWidth": 150}}, {"kind": "customsearch#result", "title": "Obamas Serve Thanksgiving Dinner to the Homeless", "htmlTitle": "Obamas Serve Thanksgiving Dinner to the Homeless", "link": "https://m.wsj.net/video/20151126/112615obathanksgiving2/112615obathanksgiving2_640x360.jpg", "displayLink": "www.wsj.com", "snippet": "Obamas Serve Thanksgiving Dinner to the Homeless", "htmlSnippet": "Obamas Serve Thanksgiving Dinner to the Homeless", "mime": "image/jpeg", "fileFormat": "image/jpeg", "image": {"contextLink": "https://www.wsj.com/video/obamas-serve-thanksgiving-dinner-to-the-homeless/3406E0AA-155A-4248-8C2C-796CCA4D472C.html", "height": 360, "width": 640, "byteSize": 39912, "thumbnailLink": "https://encrypted-tbn0.gstatic.com/images?q=tbn:ANd9GcQfE8VeoRs0-8AEpKqgkP53ViFu04v7O_BDEvlwgt-RP9RK26VGqyz6gg&s", "thumbnailHeight": 77, "thumbnailWidth": 137}}, {"kind": "customsearch#result", "title": "Obamas Serve Thanksgiving Dinner to the Homeless - MarketWatch", "htmlTitle": "Obamas Serve Thanksgiving Dinner to the Homeless - MarketWatch", "link": "https://m.wsj.net/video/20151126/112615obathanksgiving2/112615obathanksgiving2_960x540.jpg", "displayLink": "www.marketwatch.com", "snippet": "Obamas Serve Thanksgiving Dinner to the Homeless - MarketWatch", "htmlSnippet": "Obamas Serve Thanksgiving Dinner to the Homeless - MarketWatch", "mime": "image/jpeg", "fileFormat": "image/jpeg", "image": {"contextLink": "https://www.marketwatch.com/video/obamas-serve-thanksgiving-dinner-to-the-homeless/3406E0AA-155A-4248-8C2C-796CCA4D472C.html", "height": 540, "width": 960, "byteSize": 74969, "thumbnailLink": "https://encrypted-tbn0.gstatic.com/images?q=tbn:ANd9GcTP0WqeGkiqg-OMg-5cZzbmGEy4AYSvHU4NqRMTtoNc-a0VfYndMiSBLw&s", "thumbnailHeight": 83, "thumbnailWidth": 148}}]